llama_index/retrievers/pathway/__init__.py
llama_index/retrievers/pathway/base.py
llama_index_retrievers_pathway-0.4.1.dist-info/METADATA
llama_index_retrievers_pathway-0.4.1.dist-info/WHEEL
llama_index_retrievers_pathway-0.4.1.dist-info/licenses/LICENSE
llama_index_retrievers_pathway-0.4.1.dist-info/RECORD
